PC.v
module PC (
    input clk,
    input rst_n,
    output reg [31:0] pc
);
    always @(posedge clk or negedge rst_n) begin
        if (!rst_n) begin
            pc <= 32'b0; // Reset PC to 0 on reset
        end else begin
            pc <= pc + 4; // Increment PC by 4 on each clock cycle
        end
    end
endmodule

tb_PC.v
module tb_PC;

reg clk;
reg rst_n;
wire [31:0] pc;

initial begin
    $dumpfile("tb_PC.vcd");
    $dumpvars(0, uut);
    // 查看波形
    $display("Time=%0t  pc=%h", $time, pc);

end

// Instantiate the PC module
PC uut (
    .clk(clk),
    .rst_n(rst_n),
    .pc(pc)
);

// Clock generation
initial begin
    clk = 0;
    forever #5 clk = ~clk; // 10 time units period
end

// Test sequence
initial begin
    // Initialize reset
    rst_n = 0;
    #10; // Wait for 10 time units
    rst_n = 1; // Release reset
    #100; // Wait for 100 time units to observe PC increments
    $finish; // End simulation

end
endmodule

tb_PC.vcd
$date
	Mon Jun  1 22:45:22 2026
$end
$version
	Icarus Verilog
$end
$timescale
	1s
$end
$scope module tb_PC $end
$scope module uut $end
$var wire 1 ! clk $end
$var wire 1 " rst_n $end
$var reg 32 # pc [31:0] $end
$upscope $end
$upscope $end
$enddefinitions $end
$comment Show the parameter values. $end
$dumpall
$end
#0
$dumpvars
b0 #
0"
0!
$end
#5
1!
#10
0!
1"
#15
b100 #
1!
#20
0!
#25
b1000 #
1!
#30
0!
#35
b1100 #
1!
#40
0!
#45
b10000 #
1!
#50
0!
#55
b10100 #
1!
#60
0!
#65
b11000 #
1!
#70
0!
#75
b11100 #
1!
#80
0!
#85
b100000 #
1!
#90
0!
#95
b100100 #
1!
#100
0!
#105
b101000 #
1!
